basefwx/__init__.py
basefwx/__main__.py
basefwx/main.py
basefwx/yubikey_pq.py
basefwx-3.5.3.dist-info/licenses/LICENCE
basefwx-3.5.3.dist-info/METADATA
basefwx-3.5.3.dist-info/WHEEL
basefwx-3.5.3.dist-info/top_level.txt
basefwx-3.5.3.dist-info/RECORD
