Metadata-Version: 2.4
Name: basefwx
Version: 3.5.3
Summary: Take your security to the next level!
Author: F1xGOD
Author-email: F1xGOD <f1xgodim@gmail.com>
License:                     GNU GENERAL PUBLIC LICENSE
Project-URL: Homepage, https://github.com/F1xGOD/basefwx
Project-URL: Issues, https://github.com/F1xGOD/basefwx/issues
Project-URL: TermsConditions, https://www.fixcraft.org/terms-conditions
Project-URL: PrivacyPolicy, https://www.fixcraft.org/privacy-policy
Classifier: Programming Language :: Python :: 3
Classifier: License :: OSI Approved :: GNU General Public License v3 or later (GPLv3+)
Classifier: Operating System :: OS Independent
Requires-Python: >=3.10
License-File: LICENCE
Requires-Dist: cryptography>=41.0.0
Requires-Dist: numpy>=1.24.0
Requires-Dist: pillow>=10.0.0
Requires-Dist: pqcrypto>=0.3.4
Provides-Extra: argon2
Requires-Dist: argon2-cffi>=23.1.0; extra == "argon2"
Dynamic: author
Dynamic: license-file
Dynamic: requires-python
